edgetrans/__init__.py
edgetrans/edge.py
edgetrans/error.py
edgetrans/translator.py
edgetrans-0.2.3.dist-info/METADATA
edgetrans-0.2.3.dist-info/WHEEL
edgetrans-0.2.3.dist-info/RECORD
