Metadata-Version: 2.1
Name: edgetrans
Version: 0.2.3
Summary: Add your description here
Author-email: am230 <111672334+am230@users.noreply.github.com>
Requires-Python: >=3.12
Requires-Dist: aiohttp>=3.9.3
